kawaplatformlibrary/__init__.py
kawaplatformlibrary/data/__init__.py
kawaplatformlibrary/data/sentinel2dataingestion.py
kawaplatformlibrary/data/preprocessing/__init__.py
kawaplatformlibrary/data/preprocessing/obtainbbox.py
kawaplatformlibrary/data/preprocessing/splitdates.py
kawaplatformlibrary/data/preprocessing/splitgeojson.py
kawaplatformlibrary/data/preprocessing/satellitecentroids/__init__.py
kawaplatformlibrary/data/preprocessing/satellitecentroids/sentinel2_centroid_geojsons.geojson
kawaplatformlibrary/indices/__init__.py
kawaplatformlibrary/indices/bri.py
kawaplatformlibrary/indices/ccci.py
kawaplatformlibrary/indices/cigreen.py
kawaplatformlibrary/indices/dswi.py
kawaplatformlibrary/indices/evi.py
kawaplatformlibrary/indices/evi_two.py
kawaplatformlibrary/indices/gemi.py
kawaplatformlibrary/indices/lai.py
kawaplatformlibrary/indices/mtvi_one.py
kawaplatformlibrary/indices/ndre.py
kawaplatformlibrary/indices/ndvi.py
kawaplatformlibrary/indices/ndwi_crop.py
kawaplatformlibrary/indices/ndwi_surface.py
kawaplatformlibrary/indices/nli.py
kawaplatformlibrary/indices/osavi.py
kawaplatformlibrary/indices/savi.py
kawaplatformlibrary/postprocessing/__init__.py
kawaplatformlibrary/postprocessing/creatememoryraster.py
kawaplatformlibrary/postprocessing/createprofile.py
kawaplatformlibrary/postprocessing/extractarea.py
kawaplatformlibrary/postprocessing/mosiac.py
kawaplatformlibrary-1.0.4.dist-info/LICENSE.md
kawaplatformlibrary-1.0.4.dist-info/METADATA
kawaplatformlibrary-1.0.4.dist-info/WHEEL
kawaplatformlibrary-1.0.4.dist-info/top_level.txt
kawaplatformlibrary-1.0.4.dist-info/RECORD
