Metadata-Version: 2.1
Name: kawaplatformlibrary
Version: 1.0.4
Summary: Library for Data Ingestion
Home-page: https://github.com/KawaSpaceOrg/kawaplatformlibrary
Author: Gotam
Author-email: gotamdahiya@gmail.com
Requires-Python: >=3.8
Requires-Dist: joblib (>=1.2.0)
Requires-Dist: numpy (>=1.23.5)
Requires-Dist: python-dateutil (>=2.8.2)
Requires-Dist: rasterio (>=1.3.4)
Requires-Dist: requests (>=2.28.1)
Requires-Dist: scikit-learn (>=1.1.3)
Requires-Dist: Shapely (>=1.8.5.post1)
Requires-Dist: pyproj (>=3.4.0)
